[{"NRO":"1","CODIGO":"U070313492805","UND":"UND","DESCRIPCION":"MESA PARA COMPUTADORA MESA PARA COMPUTADORA DE MELAMINICO DE: 0.60*0.45*0.76 MTS.","ESTADO":"BUENO","OBSERVACION":""},{"NRO":"2","CODIGO":"U070313492806","UND":"UND","DESCRIPCION":"MESA PARA COMPUTADORA MESA PARA COMPUTADORA DE MELAMINICO DE: 0.60*0.45*0.76 MTS.","ESTADO":"BUENO","OBSERVACION":""},{"NRO":"3","CODIGO":"U070313492807","UND":"UND","DESCRIPCION":"MESA PARA COMPUTADORA MESA PARA COMPUTADORA DE MELAMINICO DE: 0.60*0.45*0.76 MTS.","ESTADO":"BUENO","OBSERVACION":"Movido 236-47"},{"NRO":"4","CODIGO":"U070313492808","UND":"UND","DESCRIPCION":"MESA PARA COMPUTADORA MESA PARA COMPUTADORA DE MELAMINICO DE: 0.60*0.45*0.76 MTS.","ESTADO":"BUENO","OBSERVACION":""},{"NRO":"5","CODIGO":"U070313492809","UND":"UND","DESCRIPCION":"MESA PARA COMPUTADORA MESA PARA COMPUTADORA DE MELAMINICO DE: 0.60*0.45*0.76 MTS.","ESTADO":"BUENO","OBSERVACION":"Movido 236-47"},{"NRO":"6","CODIGO":"U070313492811","UND":"UND","DESCRIPCION":"MESA PARA COMPUTADORA MESA PARA COMPUTADORA DE MELAMINICO DE: 0.60*0.45*0.76 MTS.","ESTADO":"BUENO","OBSERVACION":""},{"NRO":"7","CODIGO":"U070313492812","UND":"UND","DESCRIPCION":"MESA PARA COMPUTADORA MESA PARA COMPUTADORA DE MELAMINICO DE: 0.60*0.45*0.76 MTS.","ESTADO":"BUENO","OBSERVACION":"Movido 236-47"},{"NRO":"8","CODIGO":"U070313492813","UND":"UND","DESCRIPCION":"MESA PARA COMPUTADORA MESA PARA COMPUTADORA DE MELAMINICO DE: 0.60*0.45*0.76 MTS.","ESTADO":"BUENO","OBSERVACION":""},{"NRO":"9","CODIGO":"U070313492814","UND":"UND","DESCRIPCION":"MESA PARA COMPUTADORA MESA PARA COMPUTADORA DE MELAMINICO DE: 0.60*0.45*0.76 MTS.","ESTADO":"BUENO","OBSERVACION":""},{"NRO":"10","CODIGO":"U070313492815","UND":"UND","DESCRIPCION":"MESA PARA COMPUTADORA MESA PARA COMPUTADORA DE MELAMINICO DE: 0.60*0.45*0.76 MTS.","ESTADO":"BUENO","OBSERVACION":""},{"NRO":"11","CODIGO":"U070313492816","UND":"UND","DESCRIPCION":"MESA PARA COMPUTADORA MESA PARA COMPUTADORA DE MELAMINICO DE: 0.60*0.45*0.76 MTS.","ESTADO":"BUENO","OBSERVACION":""},{"NRO":"12","CODIGO":"U070313492817","UND":"UND","DESCRIPCION":"MESA PARA COMPUTADORA MESA PARA COMPUTADORA DE MELAMINICO DE: 0.60*0.45*0.76 MTS.","ESTADO":"BUENO","OBSERVACION":"Movido 236-47"},{"NRO":"13","CODIGO":"U070313492818","UND":"UND","DESCRIPCION":"MESA PARA COMPUTADORA MESA PARA COMPUTADORA DE MELAMINICO DE: 0.60*0.45*0.76 MTS.","ESTADO":"BUENO","OBSERVACION":""},{"NRO":"14","CODIGO":"U070313492819","UND":"UND","DESCRIPCION":"MESA PARA COMPUTADORA MESA PARA COMPUTADORA DE MELAMINICO DE: 0.60*0.45*0.76 MTS.","ESTADO":"BUENO","OBSERVACION":""},{"NRO":"15","CODIGO":"U070313492820","UND":"UND","DESCRIPCION":"MESA PARA COMPUTADORA MESA PARA COMPUTADORA DE MELAMINICO DE: 0.60*0.45*0.76 MTS.","ESTADO":"BUENO","OBSERVACION":"Movido 236-47"},{"NRO":"16","CODIGO":"U070313492821","UND":"UND","DESCRIPCION":"MESA PARA COMPUTADORA MESA PARA COMPUTADORA DE MELAMINICO DE: 0.60*0.45*0.76 MTS.","ESTADO":"BUENO","OBSERVACION":""},{"NRO":"17","CODIGO":"U070313492822","UND":"UND","DESCRIPCION":"MESA PARA COMPUTADORA MESA PARA COMPUTADORA DE MELAMINICO DE: 0.60*0.45*0.76 MTS.","ESTADO":"BUENO","OBSERVACION":""},{"NRO":"18","CODIGO":"U070313492823","UND":"UND","DESCRIPCION":"MESA PARA COMPUTADORA MESA PARA COMPUTADORA DE MELAMINICO DE: 0.60*0.45*0.76 MTS.","ESTADO":"BUENO","OBSERVACION":"Movido 236-47"},{"NRO":"19","CODIGO":"U070313492824","UND":"UND","DESCRIPCION":"MESA PARA COMPUTADORA MESA PARA COMPUTADORA DE MELAMINICO DE: 0.60*0.45*0.76 MTS.","ESTADO":"BUENO","OBSERVACION":""},{"NRO":"20","CODIGO":"U070313492825","UND":"UND","DESCRIPCION":"MESA PARA COMPUTADORA MESA PARA COMPUTADORA DE MELAMINICO DE: 0.60*0.45*0.76 MTS.","ESTADO":"BUENO","OBSERVACION":""},{"NRO":"21","CODIGO":"U070313492826","UND":"UND","DESCRIPCION":"MESA PARA COMPUTADORA MESA PARA COMPUTADORA DE MELAMINICO DE: 0.60*0.45*0.76 MTS.","ESTADO":"BUENO","OBSERVACION":"Movido 236-47"},{"NRO":"22","CODIGO":"U070313492827","UND":"UND","DESCRIPCION":"MESA PARA COMPUTADORA MESA PARA COMPUTADORA DE MELAMINICO DE: 0.60*0.45*0.76 MTS.","ESTADO":"BUENO","OBSERVACION":""},{"NRO":"23","CODIGO":"U070313492828","UND":"UND","DESCRIPCION":"MESA PARA COMPUTADORA MESA PARA COMPUTADORA DE MELAMINICO DE: 0.60*0.45*0.76 MTS.","ESTADO":"BUENO","OBSERVACION":""},{"NRO":"24","CODIGO":"U070313492830","UND":"UND","DESCRIPCION":"MESA PARA COMPUTADORA MESA PARA COMPUTADORA DE MELAMINICO DE: 0.60*0.45*0.76 MTS.","ESTADO":"BUENO","OBSERVACION":""},{"NRO":"25","CODIGO":"U070313492831","UND":"UND","DESCRIPCION":"MESA PARA COMPUTADORA MESA PARA COMPUTADORA DE MELAMINICO DE: 0.60*0.45*0.76 MTS.","ESTADO":"BUENO","OBSERVACION":""},{"NRO":"26","CODIGO":"U070313492832","UND":"UND","DESCRIPCION":"MESA PARA COMPUTADORA MESA PARA COMPUTADORA DE MELAMINICO DE: 0.60*0.45*0.76 MTS.","ESTADO":"BUENO","OBSERVACION":""},{"NRO":"27","CODIGO":"U070313492833","UND":"UND","DESCRIPCION":"MESA PARA COMPUTADORA MESA PARA COMPUTADORA DE MELAMINICO DE: 0.60*0.45*0.76 MTS.","ESTADO":"BUENO","OBSERVACION":""},{"NRO":"28","CODIGO":"U070313492834","UND":"UND","DESCRIPCION":"MESA PARA COMPUTADORA MESA PARA COMPUTADORA DE MELAMINICO DE: 0.60*0.45*0.76 MTS.","ESTADO":"BUENO","OBSERVACION":""},{"NRO":"29","CODIGO":"U070313492835","UND":"UND","DESCRIPCION":"MESA PARA COMPUTADORA MESA PARA COMPUTADORA DE MELAMINICO DE: 0.60*0.45*0.76 MTS.","ESTADO":"BUENO","OBSERVACION":""},{"NRO":"30","CODIGO":"U070313492836","UND":"UND","DESCRIPCION":"MESA PARA COMPUTADORA MESA PARA COMPUTADORA DE MELAMINICO DE: 0.60*0.45*0.76 MTS.","ESTADO":"BUENO","OBSERVACION":""},{"NRO":"31","CODIGO":"U070313492837","UND":"UND","DESCRIPCION":"MESA PARA COMPUTADORA MESA PARA COMPUTADORA DE MELAMINICO DE: 0.60*0.45*0.76 MTS.","ESTADO":"BUENO","OBSERVACION":"Movido 236-47"},{"NRO":"1","CODIGO":"U144771011358","UND":"UND","DESCRIPCION":"RETROPROYECTOR - PROYECTOR PROYECTOR INTERACTIVO MULTIMEDIA BRIGHTLINK 455WI","ESTADO":"REGULAR","OBSERVACION":"Movido al 236-47"}]